function_output_monitor/__init__.py
function_output_monitor/alarm.py
function_output_monitor/monitor.py
function_output_monitor-0.1.0.dist-info/LICENSE
function_output_monitor-0.1.0.dist-info/WHEEL
function_output_monitor-0.1.0.dist-info/METADATA
function_output_monitor-0.1.0.dist-info/RECORD
